{

"input":{

    "scan":{

        "identifier" : {"imageType": "CT SCAN"},

	    "crop":{
    			"method": "crop_pt_outline",
			    "params": { "structureName": "generated_pt_outline",
	                                "outStrName":"generated_pt_outline",
	                                "saveStrToPlanCFlag": 0,
	                                "outlineThreshold": -400},
	             "operator": ""
            }
    },
    "structure": {"name": "Mandible"}
},             

"passedScanDim" : "2D"

}
